.gitignore
LICENSE
MANIFEST.in
README.md
setup.py
lampost/__init__.py
lampost/db/__init__.py
lampost/db/dbconfig.py
lampost/db/dbo.py
lampost/db/dbofield.py
lampost/db/dbutil.py
lampost/db/exceptions.py
lampost/db/permissions.py
lampost/db/redisstore.py
lampost/db/registry.py
lampost/db/template.py
lampost/di/__init__.py
lampost/di/config.py
lampost/di/resource.py
lampost/editor/__init__.py
lampost/editor/admin.py
lampost/editor/editor.py
lampost/editor/session.py
lampost/gameops/__init__.py
lampost/gameops/action.py
lampost/gameops/event.py
lampost/gameops/friend.py
lampost/gameops/parser.py
lampost/gameops/script.py
lampost/gameops/target_gen.py
lampost/meta/__init__.py
lampost/meta/auto.py
lampost/meta/core.py
lampost/server/__init__.py
lampost/server/channel.py
lampost/server/display.py
lampost/server/email.py
lampost/server/handlers.py
lampost/server/message.py
lampost/server/services.py
lampost/server/session.py
lampost/server/settings.py
lampost/server/user.py
lampost/setup/__init__.py
lampost/setup/newsetup.py
lampost/setup/startargs.py
lampost/setup/tools.py
lampost/util/__init__.py
lampost/util/classes.py
lampost/util/encrypt.py
lampost/util/json.py
lampost/util/logging.py
lampost/util/lputil.py
lampost/util/pdkdf2.py
lampost_lib.egg-info/PKG-INFO
lampost_lib.egg-info/SOURCES.txt
lampost_lib.egg-info/dependency_links.txt
lampost_lib.egg-info/top_level.txt