Metadata-Version: 1.1
Name: lampost_lib
Version: 0.1.4
Summary: Multiuser environment web app framework 
Home-page: https://github.com/genzgd/lampost_lib
Author: Geoffrey D. Genz
Author-email: genzgd@gmail.com
License: MIT
Keywords: mud database
Platform: UNKNOWN
Classifier: Development Status :: 3 - Alpha
Classifier: Intended Audience :: Developers
Classifier: Topic :: Software Development :: Libraries :: Application Frameworks
Classifier: License :: OSI Approved :: MIT License
Classifier: Programming Language :: Python :: 3.4
Classifier: Programming Language :: Python :: 3.5
